maaml/Datasets/UAH_dataset/__init__.py
maaml/Datasets/UAH_dataset/dataset/UAHDataset.csv
maaml/Datasets/UAH_dataset/dataset/UAHDataset.parquet
maaml/Datasets/UAH_dataset/time_series.py
maaml/Datasets/__init__.py
maaml/__init__.py
maaml/cleaning.py
maaml/deep_learning.py
maaml/functions/Datasets/__init__.py
maaml/functions/Datasets/time_series.py
maaml/functions/__init__.py
maaml/functions/deep_learning.py
maaml/functions/machine_learning.py
maaml/functions/preprocessing.py
maaml/machine_learning.py
maaml/preprocessing.py
maaml/utils.py
maaml-0.4.9.dist-info/LICENSE
maaml-0.4.9.dist-info/WHEEL
maaml-0.4.9.dist-info/METADATA
maaml-0.4.9.dist-info/RECORD
