Metadata-Version: 2.1
Name: maaml
Version: 0.4.9
Summary: For time series datasets Machine learning pipline
License: GNU General Public License v3 (GPLv3)
Author: Najemeddine Abdennour
Requires-Python: >=3.6,<4.0
Classifier: License :: Other/Proprietary License
Classifier: Programming Language :: Python :: 3
Classifier: Programming Language :: Python :: 3.10
Classifier: Programming Language :: Python :: 3.6
Classifier: Programming Language :: Python :: 3.7
Classifier: Programming Language :: Python :: 3.8
Classifier: Programming Language :: Python :: 3.9
Requires-Dist: fastparquet (>=0.8.0,<0.9.0)
Requires-Dist: keras (>=2.7,<3.0)
Requires-Dist: matplotlib (>=3.4,<4.0)
Requires-Dist: numpy (>=1.22.0,<2.0.0)
Requires-Dist: pandas (>=1.3,<2.0)
Requires-Dist: sklearn (>=0.0,<0.1)
Requires-Dist: tensorflow (>=2.7.0,<3.0.0)
Requires-Dist: xgboost (>=1.5.2,<2.0.0)
